llm_jina_research/__init__.py
llm_researcher-0.1.0.dist-info/METADATA
llm_researcher-0.1.0.dist-info/WHEEL
llm_researcher-0.1.0.dist-info/entry_points.txt
llm_researcher-0.1.0.dist-info/top_level.txt
llm_researcher-0.1.0.dist-info/RECORD
