Metadata-Version: 2.2
Name: llm-researcher
Version: 0.1.0
Summary: LLM plugin for comprehensive research using Jina AI's Search Foundation APIs
Author-email: Thomas Hughes <irthomasthomas@gmail.com>
Project-URL: Homepage, https://github.com/simonw/llm-jina-research
Project-URL: Changelog, https://github.com/simonw/llm-jina-research/releases
Project-URL: Issues, https://github.com/simonw/llm-jina-research/issues
Classifier: License :: OSI Approved :: Apache Software License
Classifier: Programming Language :: Python :: 3.8
Classifier: Programming Language :: Python :: 3.9
Classifier: Programming Language :: Python :: 3.10
Classifier: Programming Language :: Python :: 3.11
Requires-Python: >=3.8
Provides-Extra: test
Requires-Dist: pytest>=7.0.0; extra == "test"
Requires-Dist: pytest-asyncio>=0.20.0; extra == "test"
Requires-Dist: pytest-mock>=3.0.0; extra == "test"
